fastsync/__init__.py
fastsync/app.py
fastsync/fastsync.py
fastsync/loader.py
fastsync/static/favicon.png
fastsync/static/index.html
fastsync/static/assets/index.845b2b46.js
fastsync/static/assets/index.914ee9cf.css
flashsync/__init__.py
flashsync/app.py
flashsync/flashsync.py
flashsync/loader.py
flashsync-0.1.0.dist-info/METADATA
flashsync-0.1.0.dist-info/WHEEL
flashsync-0.1.0.dist-info/entry_points.txt
flashsync-0.1.0.dist-info/top_level.txt
flashsync-0.1.0.dist-info/RECORD
